iitmbsvideosdownloader/SITES.py
iitmbsvideosdownloader/SUBJECTS.py
iitmbsvideosdownloader/__init__.py
iitmbsvideosdownloader/_downloader.py
iitmbsvideosdownloader/_functions.py
iitmbsvideosdownloader/_iitm.py
iitmbsvideosdownloader/iitmbsvideosdownloader.py
iitmbsvideosdownloader-3.1.2.dist-info/METADATA
iitmbsvideosdownloader-3.1.2.dist-info/WHEEL
iitmbsvideosdownloader-3.1.2.dist-info/RECORD
