Metadata-Version: 2.1
Name: iitmbsvideosdownloader
Version: 3.1.2
Summary: 
Author: SavindraSinghShekhawat
Author-email: shekhawatsavindra@gmail.com
Requires-Python: >=3.9.6,<4.0.0
Classifier: Programming Language :: Python :: 3
Classifier: Programming Language :: Python :: 3.10
Classifier: Programming Language :: Python :: 3.11
Classifier: Programming Language :: Python :: 3.12
Requires-Dist: chromedriver-autoinstaller-fix (>=1.0.6,<2.0.0)
Requires-Dist: selenium (>=4.21.0,<5.0.0)
